shellu/__init__.py
shellu/messages.py
shellu-0.0.1.dist-info/LICENSE
shellu-0.0.1.dist-info/METADATA
shellu-0.0.1.dist-info/WHEEL
shellu-0.0.1.dist-info/top_level.txt
shellu-0.0.1.dist-info/RECORD
