Metadata-Version: 2.1
Name: shellu
Version: 0.0.1
Summary: Package with scripts to use ANSI characters to modify the shell output.
Home-page: https://github.com/RobertoRojas/shell-utilities
Author: Roberto Rojas
Author-email: developer@robertorojas.com.mx
License: UNKNOWN
Platform: UNKNOWN
Classifier: Programming Language :: Python :: 3
Classifier: License :: OSI Approved :: MIT License
Classifier: Operating System :: OS Independent
